iar_transcriber/__init__.py
iar_transcriber/alof_consts.py
iar_transcriber/alofono.py
iar_transcriber/fon_consts.py
iar_transcriber/fonema.py
iar_transcriber/fras_consts.py
iar_transcriber/frase.py
iar_transcriber/graf_consts.py
iar_transcriber/grafema.py
iar_transcriber/pal_consts.py
iar_transcriber/palabra.py
iar_transcriber/sil_consts.py
iar_transcriber/silaba.py
iar_transcriber/testeador.py
iar_transcriber/testeador_consts.py
iar_transcriber/texto.py
iar_transcriber/transcriptor.py
iar_transcriber-1.3.1.dist-info/METADATA
iar_transcriber-1.3.1.dist-info/WHEEL
iar_transcriber-1.3.1.dist-info/top_level.txt
iar_transcriber-1.3.1.dist-info/RECORD
