Metadata-Version: 2.1
Name: iar-transcriber
Version: 1.3.1
Summary: A phonetic transcriber for Spanish language.
Home-page: https://pypi.org/project/iar-transcriber/
Author: Iván Arias Rodríguez
Author-email: ivan.arias.rodriguez@gmail.com
License: Creative Commons Attribution-NonCommercial-ShareAlike 4.0 International License
Platform: UNKNOWN
Classifier: Programming Language :: Python
Classifier: Development Status :: 1 - Planning
Classifier: Intended Audience :: Science/Research
Classifier: License :: Other/Proprietary License
Classifier: Natural Language :: Spanish
Classifier: Operating System :: OS Independent
Classifier: Programming Language :: Python :: 3 :: Only
Classifier: Topic :: Scientific/Engineering
Requires-Dist: nltk
Requires-Dist: num2words
Requires-Dist: roman
Requires-Dist: python-dateutil
Requires-Dist: iar-tokenizer
